dio_chacon_wifi_api/__init__.py
dio_chacon_wifi_api/client.py
dio_chacon_wifi_api/const.py
dio_chacon_wifi_api/exceptions.py
dio_chacon_wifi_api/session.py
dio_chacon_wifi_api-1.2.1.dist-info/LICENSE
dio_chacon_wifi_api-1.2.1.dist-info/WHEEL
dio_chacon_wifi_api-1.2.1.dist-info/METADATA
dio_chacon_wifi_api-1.2.1.dist-info/RECORD
