Metadata-Version: 2.1
Name: dio-chacon-wifi-api
Version: 1.2.1
Summary: Python library for DIO Chacon wifi's protocol for shutters and switches
Home-page: https://github.com/cnico/dio-chacon-wifi-api
License: GPL-3.0-or-later
Keywords: dio,chacon,shutter,switch,api
Author: cnico
Requires-Python: >=3.10,<4.0
Classifier: Development Status :: 5 - Production/Stable
Classifier: License :: OSI Approved :: GNU General Public License v3 or later (GPLv3+)
Classifier: Operating System :: OS Independent
Classifier: Programming Language :: Python :: 3
Classifier: Programming Language :: Python :: 3.10
Requires-Dist: aiohttp (>=3.9.3,<4.0.0)
Project-URL: Documentation, https://dio-chacon-wifi-api.readthedocs.io
Project-URL: Repository, https://github.com/cnico/dio-chacon-wifi-api
